num2words2/README.md
num2words2/__init__.py
num2words2/_version.py
num2words2/base.py
num2words2/compat.py
num2words2/currency.py
num2words2/lang_AF.py
num2words2/lang_AM.py
num2words2/lang_AR.py
num2words2/lang_AS.py
num2words2/lang_AZ.py
num2words2/lang_BA.py
num2words2/lang_BE.py
num2words2/lang_BG.py
num2words2/lang_BN.py
num2words2/lang_BO.py
num2words2/lang_BR.py
num2words2/lang_BS.py
num2words2/lang_CA.py
num2words2/lang_CE.py
num2words2/lang_CS.py
num2words2/lang_CY.py
num2words2/lang_DA.py
num2words2/lang_DE.py
num2words2/lang_EL.py
num2words2/lang_EN.py
num2words2/lang_EN_IN.py
num2words2/lang_EN_NG.py
num2words2/lang_EO.py
num2words2/lang_ES.py
num2words2/lang_ES_CO.py
num2words2/lang_ES_CR.py
num2words2/lang_ES_GT.py
num2words2/lang_ES_NI.py
num2words2/lang_ES_VE.py
num2words2/lang_ET.py
num2words2/lang_EU.py
num2words2/lang_EUR.py
num2words2/lang_FA.py
num2words2/lang_FI.py
num2words2/lang_FO.py
num2words2/lang_FR.py
num2words2/lang_FR_BE.py
num2words2/lang_FR_CH.py
num2words2/lang_FR_DZ.py
num2words2/lang_GL.py
num2words2/lang_GU.py
num2words2/lang_HA.py
num2words2/lang_HAW.py
num2words2/lang_HE.py
num2words2/lang_HI.py
num2words2/lang_HR.py
num2words2/lang_HT.py
num2words2/lang_HU.py
num2words2/lang_HY.py
num2words2/lang_ID.py
num2words2/lang_IS.py
num2words2/lang_IT.py
num2words2/lang_JA.py
num2words2/lang_JW.py
num2words2/lang_KA.py
num2words2/lang_KK.py
num2words2/lang_KM.py
num2words2/lang_KN.py
num2words2/lang_KO.py
num2words2/lang_KZ.py
num2words2/lang_LA.py
num2words2/lang_LB.py
num2words2/lang_LN.py
num2words2/lang_LO.py
num2words2/lang_LT.py
num2words2/lang_LV.py
num2words2/lang_MG.py
num2words2/lang_MI.py
num2words2/lang_MK.py
num2words2/lang_ML.py
num2words2/lang_MN.py
num2words2/lang_MR.py
num2words2/lang_MS.py
num2words2/lang_MT.py
num2words2/lang_MY.py
num2words2/lang_NE.py
num2words2/lang_NL.py
num2words2/lang_NN.py
num2words2/lang_NO.py
num2words2/lang_OC.py
num2words2/lang_PA.py
num2words2/lang_PL.py
num2words2/lang_PS.py
num2words2-0.1.0.dev1.dist-info/licenses/COPYING
num2words2-0.1.0.dev1.dist-info/METADATA
num2words2-0.1.0.dev1.dist-info/WHEEL
num2words2-0.1.0.dev1.dist-info/entry_points.txt
num2words2-0.1.0.dev1.dist-info/top_level.txt
num2words2-0.1.0.dev1.dist-info/RECORD
