Metadata-Version: 2.4
Name: num2words2
Version: 0.1.0.dev1
Summary: Modern, actively maintained fork of num2words optimized for LLM/AI/speech applications.
Home-page: https://github.com/jqueguiner/num2words
Author: Jean-Louis Queguiner
Author-email: Jean-Louis Queguiner <jean-louis.queguiner@gmail.com>
Maintainer: Jean-Louis Queguiner
Maintainer-email: Jean-Louis Queguiner <jean-louis.queguiner@gmail.com>
License: LGPL-2.1
Project-URL: Homepage, https://github.com/jqueguiner/num2words
Project-URL: Repository, https://github.com/jqueguiner/num2words.git
Project-URL: Bug Tracker, https://github.com/jqueguiner/num2words/issues
Keywords: number,word,numbers,words,convert,conversion,i18n,localisation,localization,internationalisation,internationalization
Classifier: Development Status :: 5 - Production/Stable
Classifier: Intended Audience :: Developers
Classifier: Programming Language :: Python :: 3
Classifier: Programming Language :: Python :: 3.8
Classifier: Programming Language :: Python :: 3.9
Classifier: Programming Language :: Python :: 3.10
Classifier: Programming Language :: Python :: 3.11
Classifier: Programming Language :: Python :: 3.12
Classifier: Programming Language :: Python :: 3.13
Classifier: Topic :: Software Development :: Internationalization
Classifier: Topic :: Software Development :: Libraries :: Python Modules
Classifier: Topic :: Software Development :: Localization
Classifier: Topic :: Text Processing :: Linguistic
Requires-Python: >=3.8
License-File: COPYING
Requires-Dist: docopt>=0.6.2
Dynamic: author
Dynamic: home-page
Dynamic: license
Dynamic: license-file
Dynamic: maintainer
